{"nodes": [{"id": "c_users_jyot2_atlas_dashboard_src_hooks_usewebsocket_ts", "label": "useWebSocket.ts", "file_type": "code", "source_file": "C:\\Users\\jyot2\\atlas\\dashboard\\src\\hooks\\useWebSocket.ts", "source_location": "L1"}, {"id": "usewebsocket_usewebsocket", "label": "useWebSocket()", "file_type": "code", "source_file": "C:\\Users\\jyot2\\atlas\\dashboard\\src\\hooks\\useWebSocket.ts", "source_location": "L15"}], "edges": [{"source": "c_users_jyot2_atlas_dashboard_src_hooks_usewebsocket_ts", "target": "react", "relation": "imports_from", "confidence": "EXTRACTED", "source_file": "C:\\Users\\jyot2\\atlas\\dashboard\\src\\hooks\\useWebSocket.ts", "source_location": "L2", "weight": 1.0}, {"source": "c_users_jyot2_atlas_dashboard_src_hooks_usewebsocket_ts", "target": "usewebsocket_usewebsocket", "relation": "contains", "confidence": "EXTRACTED", "source_file": "C:\\Users\\jyot2\\atlas\\dashboard\\src\\hooks\\useWebSocket.ts", "source_location": "L15", "weight": 1.0}]}